<?xml version="1.0" encoding="UTF-8"?>
<!-- Created by COPASI version 4.19 (Build 140) on 2017-03-24 18:20 with libSBML version 5.13.0. -->
<sbml xmlns="http://www.sbml.org/sbml/level2/version3" level="2" version="3">
  <model metaid="COPASI1" id="Model_1" name="New Model_1">
    <listOfUnitDefinitions>
      <unitDefinition id="volume" name="volume">
        <listOfUnits>
          <unit kind="litre" scale="-3"/>
        </listOfUnits>
      </unitDefinition>
      <unitDefinition id="substance" name="substance">
        <listOfUnits>
          <unit kind="mole" scale="-3"/>
        </listOfUnits>
      </unitDefinition>
      <unitDefinition id="unit_0">
        <listOfUnits>
          <unit kind="second" exponent="-1"/>
        </listOfUnits>
      </unitDefinition>
    </listOfUnitDefinitions>
    <listOfCompartments>
      <compartment id="compartment_1" name="compartment" spatialDimensions="3" size="1" constant="true"/>
    </listOfCompartments>
    <listOfSpecies>
      <species metaid="COPASI2" id="species_1" name="A" compartment="compartment_1" initialConcentration="1" boundaryCondition="false" constant="false"/>
      <species metaid="COPASI3" id="species_2" name="B" compartment="compartment_1" initialConcentration="0" boundaryCondition="false" constant="false"/>
      <species metaid="COPASI4" id="species_3" name="C" compartment="compartment_1" initialConcentration="0" boundaryCondition="false" constant="false"/>
    </listOfSpecies>
    <listOfReactions>
      <reaction metaid="COPASI5" id="reaction_1" name="reaction_1" reversible="false">
        <listOfReactants>
          <speciesReference species="species_1" stoichiometry="1"/>
        </listOfReactants>
        <listOfProducts>
          <speciesReference species="species_2" stoichiometry="1"/>
        </listOfProducts>
        <kineticLaw>
          <math xmlns="http://www.w3.org/1998/Math/MathML">
            <apply>
              <times/>
              <ci> compartment_1 </ci>
              <ci> k1 </ci>
              <ci> species_1 </ci>
            </apply>
          </math>
          <listOfParameters>
            <parameter id="k1" name="k1" value="0.2"/>
          </listOfParameters>
        </kineticLaw>
      </reaction>
      <reaction metaid="COPASI6" id="reaction_2" name="reaction_2" reversible="false">
        <listOfReactants>
          <speciesReference species="species_2" stoichiometry="1"/>
        </listOfReactants>
        <listOfProducts>
          <speciesReference species="species_3" stoichiometry="1"/>
        </listOfProducts>
        <kineticLaw>
          <math xmlns="http://www.w3.org/1998/Math/MathML">
            <apply>
              <times/>
              <ci> compartment_1 </ci>
              <ci> k1 </ci>
              <ci> species_2 </ci>
            </apply>
          </math>
          <listOfParameters>
            <parameter id="k1" name="k1" value="0.1"/>
          </listOfParameters>
        </kineticLaw>
      </reaction>
    </listOfReactions>
  </model>
</sbml>
